{
  "manifest": {
    "publishingInformation": {
      "locales": {
        "ja-JP": {
          "summary": "Garoxaだよ",
          "examplePhrases": [
            "アレクサ、ガルーン予定管理を開いて",
            "アレクサ、ガルーン予定管理"
          ],
          "name": "Garoxa",
          "description": "Garoonに予定を登録するぜ！"
        }
      },
      "isAvailableWorldwide": true,
      "testingInstructions": "Sample Testing Instructions.",
      "category": "KNOWLEDGE_AND_TRIVIA",
      "distributionCountries": []
    },
    "apis": {
      "custom": {
        "endpoint": {
          "uri": "arn:aws:lambda:ap-northeast-1:568211859639:function:ask-garoxa-default-skillStack-1-AlexaSkillFunction-110NONTU3DDEQ"
        }
      }
    },
    "manifestVersion": "1.0"
  }
}